README.md
setup.py
homectl/__init__.py
homectl/__version__.py
homectl/cli.py
homectl/config.py
homectl/config_ifttt.py
homectl/homectl.py
homectl.egg-info/PKG-INFO
homectl.egg-info/SOURCES.txt
homectl.egg-info/dependency_links.txt
homectl.egg-info/entry_points.txt
homectl.egg-info/requires.txt
homectl.egg-info/top_level.txt
tests/__init__.py
tests/sanity_test.py