Metadata-Version: 2.1
Name: homectl
Version: 0.1.0
Summary: Command line smart device control
Home-page: https://github.com/cmccandless/homectl
Author: Corey McCandless
Author-email: crm1994@gmail.com
License: UNKNOWN
Platform: UNKNOWN
Classifier: Programming Language :: Python :: 3
Classifier: License :: OSI Approved :: MIT License
Classifier: Operating System :: OS Independent
